aic_core/__init__.py
aic_core/logging.py
aic_core/py.typed
aic_core/agent/agent.py
aic_core/agent/agent_hub.py
aic_core/agent/result_types.py
aic_core/mcp/feedly/__init__.py
aic_core/mcp/feedly/server.py
aic_core/streamlit/agent_config.py
aic_core/streamlit/agent_page.py
aic_core/streamlit/mixins.py
aic_core/streamlit/page.py
aic_core/streamlit/tool_config.py
aic_core/streamlit/tool_template.py
aic_core-0.0.4.dist-info/METADATA
aic_core-0.0.4.dist-info/WHEEL
aic_core-0.0.4.dist-info/entry_points.txt
aic_core-0.0.4.dist-info/licenses/LICENSE
aic_core-0.0.4.dist-info/RECORD
