Metadata-Version: 2.4
Name: aic-core
Version: 0.0.4
Summary: An Agentic platform that allows you to define extensions
Author-email: Shaojie Jiang <shaojie.jiang1@gmail.com>
License: MIT License
License-File: LICENSE
Requires-Python: >=3.12
Requires-Dist: feedly-client
Requires-Dist: httpx>=0.28.1
Requires-Dist: huggingface-hub>=0.29.3
Requires-Dist: logfire>=3.11.0
Requires-Dist: mcp[cli]>=1.5.0
Requires-Dist: pydantic-ai>=0.2.3
Requires-Dist: pydantic>=2.10.6
Requires-Dist: smolagents>=1.11.0
Requires-Dist: streamlit-code-editor>=0.1.22
Requires-Dist: streamlit>=1.44.0
